geometryai/__init__.py
geometryai/core.py
geometryai-0.0.4.dist-info/METADATA
geometryai-0.0.4.dist-info/WHEEL
geometryai-0.0.4.dist-info/top_level.txt
geometryai-0.0.4.dist-info/RECORD
