Metadata-Version: 2.4
Name: geometryai
Version: 0.0.4
Summary: solve euclid geometry
Author: Your Name
Author-email: you@example.com
Requires-Python: >=3.8
Dynamic: author
Dynamic: author-email
Dynamic: requires-python
Dynamic: summary
